README.rst
setup.py
superhex/__init__.py
superhex/superhex.py
superhex.egg-info/PKG-INFO
superhex.egg-info/SOURCES.txt
superhex.egg-info/dependency_links.txt
superhex.egg-info/requires.txt
superhex.egg-info/top_level.txt